{
	"configurations" : 
	[
		{
			"directories" : 
			[
				{
					"build" : ".",
					"jsonFile" : "directory-.-Debug-f5ebdc15457944623624.json",
					"minimumCMakeVersion" : 
					{
						"string" : "3.20"
					},
					"projectIndex" : 0,
					"source" : ".",
					"targetIndexes" : 
					[
						0,
						1
					]
				}
			],
			"name" : "Debug",
			"projects" : 
			[
				{
					"directoryIndexes" : 
					[
						0
					],
					"name" : "spvector",
					"targetIndexes" : 
					[
						0,
						1
					]
				}
			],
			"targets" : 
			[
				{
					"directoryIndex" : 0,
					"id" : "matrix-child::@6890427a1f51a3e7e1df",
					"jsonFile" : "target-matrix-child-Debug-9e0e848b411a0aa3c9f5.json",
					"name" : "matrix-child",
					"projectIndex" : 0
				},
				{
					"directoryIndex" : 0,
					"id" : "matrix-parent::@6890427a1f51a3e7e1df",
					"jsonFile" : "target-matrix-parent-Debug-771deb7379694bde3e90.json",
					"name" : "matrix-parent",
					"projectIndex" : 0
				}
			]
		}
	],
	"kind" : "codemodel",
	"paths" : 
	{
		"build" : "/home/erina/Digipen/CS180/MultiProcessMatrix/cmake-build-debug",
		"source" : "/home/erina/Digipen/CS180/MultiProcessMatrix"
	},
	"version" : 
	{
		"major" : 2,
		"minor" : 7
	}
}
